easyimporting.py
easyimporting-0.1.6.dist-info/METADATA
easyimporting-0.1.6.dist-info/WHEEL
easyimporting-0.1.6.dist-info/top_level.txt
easyimporting-0.1.6.dist-info/RECORD
