Metadata-Version: 2.1
Name: easyimporting
Version: 0.1.6
Summary: install module if module isn't install
Home-page: UNKNOWN
License: UNKNOWN
Platform: UNKNOWN
